pyodide_http/__init__.py
pyodide_http/_core.py
pyodide_http/_requests.py
pyodide_http/_streaming.py
pyodide_http/_urllib.py
pyodide_http-0.2.2.dist-info/LICENSE
pyodide_http-0.2.2.dist-info/METADATA
pyodide_http-0.2.2.dist-info/WHEEL
pyodide_http-0.2.2.dist-info/top_level.txt
pyodide_http-0.2.2.dist-info/RECORD
