Metadata-Version: 2.1
Name: pyodide_http
Version: 0.2.2
Summary: Patch requests, urllib and urllib3 to make them work in Pyodide
Home-page: https://github.com/koenvo/pyodide-http
Author: Koen Vossen
Author-email: info@koenvossen.nl
License: MIT
License-File: LICENSE
